helix_platform_api_public_client_legacy/__init__.py
helix_platform_api_public_client_legacy/api_client.py
helix_platform_api_public_client_legacy/api_response.py
helix_platform_api_public_client_legacy/configuration.py
helix_platform_api_public_client_legacy/exceptions.py
helix_platform_api_public_client_legacy/py.typed
helix_platform_api_public_client_legacy/rest.py
helix_platform_api_public_client_legacy/api/__init__.py
helix_platform_api_public_client_legacy/api/attachment_api.py
helix_platform_api_public_client_legacy/api/audit_log_api.py
helix_platform_api_public_client_legacy/api/default_nomination_api.py
helix_platform_api_public_client_legacy/api/manual_file_upload_api.py
helix_platform_api_public_client_legacy/api/messages_api.py
helix_platform_api_public_client_legacy/api/metadata_api.py
helix_platform_api_public_client_legacy/api/nomination_api.py
helix_platform_api_public_client_legacy/api/nomination_gate_api.py
helix_platform_api_public_client_legacy/api/organisation_api.py
helix_platform_api_public_client_legacy/api/participant_dashboard_api.py
helix_platform_api_public_client_legacy/api/participant_overview_api.py
helix_platform_api_public_client_legacy/api/profile_api.py
helix_platform_api_public_client_legacy/api/public_overview_api.py
helix_platform_api_public_client_legacy/api/reporting_api.py
helix_platform_api_public_client_legacy/api/transmission_right_api.py
helix_platform_api_public_client_legacy/api/user_api.py
helix_platform_api_public_client_legacy/models/__init__.py
helix_platform_api_public_client_legacy/models/aggregated_nomination_options.py
helix_platform_api_public_client_legacy/models/aggregated_nomination_options_nominee_participants.py
helix_platform_api_public_client_legacy/models/aggregated_nominations.py
helix_platform_api_public_client_legacy/models/aggregated_nominations_values.py
helix_platform_api_public_client_legacy/models/aggregated_nominations_values_mtus.py
helix_platform_api_public_client_legacy-1.2.0.dist-info/METADATA
helix_platform_api_public_client_legacy-1.2.0.dist-info/WHEEL
helix_platform_api_public_client_legacy-1.2.0.dist-info/top_level.txt
helix_platform_api_public_client_legacy-1.2.0.dist-info/RECORD
