Metadata-Version: 2.1
Name: helix-platform-api-public-client-legacy
Version: 1.2.0
Summary: Platform API
Home-page: 
Author: ElecLink
Author-email: team.eleclink@eleclink.co.uk
Keywords: OpenAPI,OpenAPI-Generator,Platform API
Requires-Dist: aenum
Requires-Dist: pydantic (<2,>=1.10.5)
Requires-Dist: python-dateutil
Requires-Dist: urllib3 (<3.0.0,>=1.25.3)
